_geoslib.cp313-win_amd64.pyd
geos_c.dll
basemap-2.0.0.dist-info/licenses/LICENSE
basemap-2.0.0.dist-info/licenses/LICENSE.geos
mpl_toolkits/basemap/__init__.py
mpl_toolkits/basemap/cm.py
mpl_toolkits/basemap/diagnostic.py
mpl_toolkits/basemap/proj.py
mpl_toolkits/basemap/solar.py
basemap-2.0.0.dist-info/METADATA
basemap-2.0.0.dist-info/WHEEL
basemap-2.0.0.dist-info/top_level.txt
basemap-2.0.0.dist-info/RECORD
