Metadata-Version: 2.4
Name: basemap
Version: 2.0.0
Summary: Plot data on map projections with matplotlib
Author: Jeff Whitaker
Author-email: jeffrey.s.whitaker@noaa.gov
Maintainer: The Matplotlib development team
Maintainer-email: matplotlib-users@python.org
License: MIT
Project-URL: Homepage, https://github.com/matplotlib/basemap
Project-URL: Documentation, https://matplotlib.org/basemap
Project-URL: Repository, https://github.com/matplotlib/basemap.git
Project-URL: Issues, https://github.com/matplotlib/basemap/issues
Keywords: GIS,maps,plots
Classifier: Development Status :: 5 - Production/Stable
Classifier: Intended Audience :: Education
Classifier: Intended Audience :: Science/Research
Classifier: Operating System :: OS Independent
Classifier: Programming Language :: Python :: 3
Classifier: Topic :: Scientific/Engineering :: Visualization
Classifier: Topic :: Software Development :: Libraries :: Python Modules
Requires-Python: >=3.9, <3.14
License-File: LICENSE
License-File: LICENSE.geos
Requires-Dist: basemap_data<3.0,>=2.0
Requires-Dist: packaging<26.0,>=20.5
Requires-Dist: numpy<2.4,>=2.0
Requires-Dist: matplotlib<3.11,>=3.4
Requires-Dist: pyproj<3.8,>=3.0
Requires-Dist: pyshp<2.4,>=2.0
Provides-Extra: doc
Requires-Dist: sphinx<8.0,>=7.0; extra == "doc"
Requires-Dist: furo<2024.8.7,>=2023.9.10; extra == "doc"
Requires-Dist: scipy<1.16,>=1.6; extra == "doc"
Requires-Dist: cftime<1.7.0,>=1.4.0; extra == "doc"
Requires-Dist: netCDF4<1.8.0,>=1.5.6; extra == "doc"
Provides-Extra: lint
Requires-Dist: flake8<7.3,>=3.9; extra == "lint"
Requires-Dist: flake8-pyproject<1.3,>=1.0; extra == "lint"
Requires-Dist: astroid<3.4,>=3.0; extra == "lint"
Requires-Dist: pylint<3.4,>=3.0; extra == "lint"
Provides-Extra: test
Requires-Dist: pytest<8.5,>=7.0; extra == "test"
Requires-Dist: pytest-cov<6.3,>=3.0; extra == "test"
Requires-Dist: coverage[toml]<7.10,>=5.0; extra == "test"
Provides-Extra: owslib
Requires-Dist: OWSLib<0.35,>=0.28.1; extra == "owslib"
Dynamic: author
Dynamic: author-email
Dynamic: classifier
Dynamic: description
Dynamic: description-content-type
Dynamic: keywords
Dynamic: license
Dynamic: license-file
Dynamic: maintainer
Dynamic: maintainer-email
Dynamic: project-url
Dynamic: provides-extra
Dynamic: requires-dist
Dynamic: requires-python
Dynamic: summary
